owui_utilities/__init__.py
owui_utilities/parameter_confirm.py
owui_utilities-0.0.4.dist-info/METADATA
owui_utilities-0.0.4.dist-info/WHEEL
owui_utilities-0.0.4.dist-info/RECORD
