Metadata-Version: 2.3
Name: owui-utilities
Version: 0.0.4
Summary: Simple Open WebUI utilities to be added to and reused across local OWUI tools 
License: MIT
Author: Robert Ranney
Author-email: robert.ranney@caci.com
Requires-Python: >=3.8
Classifier: Programming Language :: Python
Classifier: Programming Language :: Python :: 3.8
Classifier: Programming Language :: Python :: 3.9
Classifier: Programming Language :: Python :: 3.10
Classifier: Programming Language :: Python :: 3.11
Classifier: Programming Language :: Python :: 3.12
Classifier: Programming Language :: Python :: Implementation :: CPython
Classifier: Programming Language :: Python :: Implementation :: PyPy
Requires-Dist: pydantic
